andclust/__init__.py
andclust/core.py
andclust-1.0.5.dist-info/licenses/LICENSE
andclust-1.0.5.dist-info/METADATA
andclust-1.0.5.dist-info/WHEEL
andclust-1.0.5.dist-info/top_level.txt
andclust-1.0.5.dist-info/RECORD
