Metadata-Version: 2.4
Name: andclust
Version: 1.0.5
Summary: ANDClust: Adaptive Neighborhood Density-Based Clustering Algorithm
Author-email: Ali Şenol <alisenol@tarsus.edu.tr>
License: MIT License
Project-URL: Homepage, https://github.com/senolali/andclust
Project-URL: Documentation, https://github.com/senolali/andclust
Project-URL: Source, https://github.com/senolali/andclust
Project-URL: Issues, https://github.com/senolali/andclust
Project-URL: Paper, https://doi.org/10.1002/adts.202301113
Keywords: clustering,density-based,machine-learning,unsupervised-learning,andclust,neighborhood-density
Classifier: Development Status :: 5 - Production/Stable
Classifier: Intended Audience :: Science/Research
Classifier: Intended Audience :: Developers
Classifier: License :: OSI Approved :: MIT License
Classifier: Programming Language :: Python
Classifier: Programming Language :: Python :: 3
Classifier: Programming Language :: Python :: 3.8
Classifier: Programming Language :: Python :: 3.9
Classifier: Programming Language :: Python :: 3.10
Classifier: Programming Language :: Python :: 3.11
Classifier: Programming Language :: Python :: 3.12
Classifier: Topic :: Scientific/Engineering :: Artificial Intelligence
Classifier: Topic :: Scientific/Engineering :: Information Analysis
Classifier: Topic :: Scientific/Engineering :: Mathematics
Requires-Python: >=3.8
License-File: LICENSE
Requires-Dist: numpy>=1.20
Requires-Dist: scikit-learn>=1.0
Requires-Dist: scipy>=1.8
Requires-Dist: matplotlib>=3.0
Dynamic: license-file
